Workbook

Sheet Línea Recta
B2: MÉTODO DE LÍNEA RECTA
B4: Valor Activo | C4: 80000000 | G4: Periodo | H4: Utilidad Bruta | I4: Dep Periodo | J4: EBIT | K4: Impuestos
B5: Valor Salvamento | C5: 10000000 | G5: 1 | H5: 100000000
B6: Vida Útil | C6: 10 | G6: =G5+1 -> 2 | H6: 100000000
G7: =G6+1 -> 3 | H7: 100000000
G8: =G7+1 -> 4 | H8: 100000000
G9: =G8+1 -> 5 | H9: 100000000
G10: =G9+1 -> 6 | H10: 100000000
G11: =G10+1 -> 7 | H11: 100000000
G12: =G11+1 -> 8 | H12: 100000000
B13: Periodo | C13: Dep. Periodo | D13: Dep. Acumulada | E13: Valor Libros | G13: =G12+1 -> 9 | H13: 100000000
B14: 0 | G14: =G13+1 -> 10 | H14: 100000000
B15: =B14+1 -> 1
B16: =B15+1 -> 2 | G16: Costo de Oportunidad | H16: 0.1 | I16: EA
B17: =B16+1 -> 3 | G17: Tasa Impositiva | H17: 0.35
B18: =B17+1 -> 4
B19: =B18+1 -> 5 | G19: VP Impuestos
B20: =B19+1 -> 6 | G20: Suma Impuestos
B21: =B20+1 -> 7
B22: =B21+1 -> 8
B23: =B22+1 -> 9
B24: =B23+1 -> 10

Sheet Reducción de Saldos
B2: MÉTODO DE REDUCCIÓN DE SALDOS
B4: Valor Activo | C4: 80000000 | G4: Periodo | H4: Utilidad Bruta | I4: Dep Periodo | J4: EBIT | K4: Impuestos
B5: Valor Salvamento | C5: 10000000 | G5: 1 | H5: 100000000
B6: Vida Útil | C6: 10 | G6: =G5+1 -> 2 | H6: 100000000
G7: =G6+1 -> 3 | H7: 100000000
G8: =G7+1 -> 4 | H8: 100000000
G9: =G8+1 -> 5 | H9: 100000000
G10: =G9+1 -> 6 | H10: 100000000
G11: =G10+1 -> 7 | H11: 100000000
G12: =G11+1 -> 8 | H12: 100000000
B13: Periodo | C13: Dep. Periodo | D13: Dep. Acumulada | E13: Valor Libros | G13: =G12+1 -> 9 | H13: 100000000
B14: 0 | G14: =G13+1 -> 10 | H14: 100000000
B15: =B14+1 -> 1
B16: =B15+1 -> 2 | G16: Costo de Oportunidad | H16: 0.1 | I16: EA
B17: =B16+1 -> 3 | G17: Tasa Impositiva | H17: 0.35
B18: =B17+1 -> 4
B19: =B18+1 -> 5 | G19: VP Impuestos
B20: =B19+1 -> 6 | G20: Suma Impuestos
B21: =B20+1 -> 7
B22: =B21+1 -> 8
B23: =B22+1 -> 9
B24: =B23+1 -> 10

Sheet Unidades Productivas
B2: MÉTODO DE UNIDADES PRODUCTIVAS
B4: Valor Activo | C4: 80000000 | H4: Periodo | I4: Utilidad Bruta | J4: Dep Periodo | K4: EBIT | L4: Impuestos
B5: Valor Salvamento | C5: 10000000 | H5: 1 | I5: 100000000
B6: Vida Útil | C6: 10 | H6: =H5+1 -> 2 | I6: 100000000
H7: =H6+1 -> 3 | I7: 100000000
H8: =H7+1 -> 4 | I8: 100000000
H9: =H8+1 -> 5 | I9: 100000000
H10: =H9+1 -> 6 | I10: 100000000
H11: =H10+1 -> 7 | I11: 100000000
H12: =H11+1 -> 8 | I12: 100000000
B13: Periodo | C13: Unidades | D13: Dep. Periodo | E13: Dep. Acumulada | F13: Valor Libros | H13: =H12+1 -> 9 | I13: 100000000
B14: 0 | H14: =H13+1 -> 10 | I14: 100000000
B15: =B14+1 -> 1 | C15: 600
B16: =B15+1 -> 2 | C16: 1200 | H16: Costo de Oportunidad | I16: 0.1 | J16: EA
B17: =B16+1 -> 3 | C17: 2400 | H17: Tasa Impositiva | I17: 0.35
B18: =B17+1 -> 4 | C18: 2800
B19: =B18+1 -> 5 | C19: 3000 | H19: VP Impuestos
B20: =B19+1 -> 6 | C20: 3000 | H20: Suma Impuestos
B21: =B20+1 -> 7 | C21: 2800
B22: =B21+1 -> 8 | C22: 2400
B23: =B22+1 -> 9 | C23: 1200
B24: =B23+1 -> 10 | C24: 600
B25: Capacidad Máxima | C25: =SUM(C15:C24) -> 20000

Sheet Comparación
B3: Método de Depreciación | C3: Suma Impuestos | D3: VP Impuestos | G3: Se pagan menos impuestos con Reducción de Saldos, el cual es un método de depreciación ACELERADO (se deprecia más al comienzo de la vida útil del activo que al final).
B4: Línea Recta | C4: ='Línea Recta'!H20 -> 0 | D4: ='Línea Recta'!H19 -> 0
B5: Reducción de Saldos | C5: ='Reducción de Saldos'!H20 -> 0 | D5: ='Reducción de Saldos'!H19 -> 0
B6: Unidades Productivas | C6: ='Unidades Productivas'!I20 -> 0 | D6: ='Unidades Productivas'!I19 -> 0
B8: Comparativo de Métodos de Depreciación
B10: Periodo | C10: Línea Recta | D10: Reducción de Saldos | E10: Unidades Productivas
B11: 1 | C11: ='Línea Recta'!C15 -> 0 | D11: ='Reducción de Saldos'!C15 -> 0 | E11: ='Unidades Productivas'!D15 -> 0
B12: =B11+1 -> 2 | C12: ='Línea Recta'!C16 -> 0 | D12: ='Reducción de Saldos'!C16 -> 0 | E12: ='Unidades Productivas'!D16 -> 0
B13: =B12+1 -> 3 | C13: ='Línea Recta'!C17 -> 0 | D13: ='Reducción de Saldos'!C17 -> 0 | E13: ='Unidades Productivas'!D17 -> 0
B14: =B13+1 -> 4 | C14: ='Línea Recta'!C18 -> 0 | D14: ='Reducción de Saldos'!C18 -> 0 | E14: ='Unidades Productivas'!D18 -> 0
B15: =B14+1 -> 5 | C15: ='Línea Recta'!C19 -> 0 | D15: ='Reducción de Saldos'!C19 -> 0 | E15: ='Unidades Productivas'!D19 -> 0
B16: =B15+1 -> 6 | C16: ='Línea Recta'!C20 -> 0 | D16: ='Reducción de Saldos'!C20 -> 0 | E16: ='Unidades Productivas'!D20 -> 0
B17: =B16+1 -> 7 | C17: ='Línea Recta'!C21 -> 0 | D17: ='Reducción de Saldos'!C21 -> 0 | E17: ='Unidades Productivas'!D21 -> 0
B18: =B17+1 -> 8 | C18: ='Línea Recta'!C22 -> 0 | D18: ='Reducción de Saldos'!C22 -> 0 | E18: ='Unidades Productivas'!D22 -> 0
B19: =B18+1 -> 9 | C19: ='Línea Recta'!C23 -> 0 | D19: ='Reducción de Saldos'!C23 -> 0 | E19: ='Unidades Productivas'!D23 -> 0
B20: =B19+1 -> 10 | C20: ='Línea Recta'!C24 -> 0 | D20: ='Reducción de Saldos'!C24 -> 0 | E20: ='Unidades Productivas'!D24 -> 0
